pulire/__init__.py
pulire/column.py
pulire/formatter.py
pulire/formatters/__init__.py
pulire/formatters/decimals.py
pulire/schema.py
pulire/utils.py
pulire/validator.py
pulire/validators/__init__.py
pulire/validators/greater.py
pulire/validators/isin.py
pulire/validators/less.py
pulire/validators/max_diff.py
pulire/validators/max_fall.py
pulire/validators/max_peak.py
pulire/validators/max_rise.py
pulire/validators/maximum.py
pulire/validators/minimum.py
pulire/validators/regex.py
pulire/validators/required.py
pulire/validators/requires.py
pulire-0.0.9.dist-info/LICENSE
pulire-0.0.9.dist-info/METADATA
pulire-0.0.9.dist-info/WHEEL
pulire-0.0.9.dist-info/RECORD
