Metadata-Version: 2.3
Name: pulire
Version: 0.0.9
Summary: A lightweight DataFrame validation library.
Author: Meteostat
Author-email: info@meteostat.net
Requires-Python: >=3.9,<4.0
Classifier: Programming Language :: Python :: 3
Classifier: Programming Language :: Python :: 3.9
Classifier: Programming Language :: Python :: 3.10
Classifier: Programming Language :: Python :: 3.11
Classifier: Programming Language :: Python :: 3.12
Classifier: Programming Language :: Python :: 3.13
Requires-Dist: numpy (>=1)
Requires-Dist: pandas (>=1)
